{"v":"5.7.8","fr":60,"ip":0,"op":601,"w":1440,"h":1456,"nm":"Frame 4","ddd":0,"assets":[],"layers":[{"ddd":0,"ind":1,"ty":4,"nm":"1","sr":1,"ks":{"o":{"a":1,"k":[{"i":{"x":[0.833],"y":[0.833]},"o":{"x":[0.167],"y":[0.167]},"t":60,"s":[100]},{"t":120,"s":[40]}],"ix":11},"r":{"a":0,"k":0,"ix":10},"p":{"a":0,"k":[339,273,0],"ix":2,"l":2},"a":{"a":0,"k":[0,0,0],"ix":1,"l":2},"s":{"a":0,"k":[200,200,100],"ix":6,"l":2}},"ao":0,"shapes":[{"ty":"gr","it":[{"ind":0,"ty":"sh","ix":1,"ks":{"a":0,"k":{"i":[[0,0],[0,0],[0,0],[0,0],[0,0],[0,0],[0,0],[0,0],[0,0],[0,0]],"o":[[0,0],[0,0],[0,0],[0,0],[0,0],[0,0],[0,0],[0,0],[0,0],[0,0]],"v":[[-17.74,-6.445],[-22.614,-6.445],[-22.614,1.31],[-21.506,1.31],[-21.506,-1.869],[-18.183,-1.869],[-18.183,-2.977],[-21.506,-2.977],[-21.506,-5.337],[-17.74,-5.337]],"c":true},"ix":2},"nm":"F","mn":"ADBE Vector Shape - Group","hd":false},{"ty":"fl","c":{"a":0,"k":[0.161849990546,0.161849990546,0.161849990546,1],"ix":4},"o":{"a":0,"k":100,"ix":5},"r":1,"bm":0,"nm":"Fill 1","mn":"ADBE Vector Graphic - Fill","hd":false},{"ty":"tr","p":{"a":0,"k":[0,0],"ix":2},"a":{"a":0,"k":[0,0],"ix":1},"s":{"a":0,"k":[100,100],"ix":3},"r":{"a":0,"k":0,"ix":6},"o":{"a":0,"k":100,"ix":7},"sk":{"a":0,"k":0,"ix":4},"sa":{"a":0,"k":0,"ix":5},"nm":"Transform"}],"nm":"F","np":3,"cix":2,"bm":0,"ix":1,"mn":"ADBE Vector Group","hd":false},{"ty":"gr","it":[{"ind":0,"ty":"sh","ix":1,"ks":{"a":0,"k":{"i":[[0,0],[1.075,0],[0,0],[0,-1.108],[0,0],[-1.097,0],[0,0],[0,1.097],[0,0],[0,0],[0,0],[0.487,0],[0,0],[0,0.487],[0,0],[0,0]],"o":[[-0.055,-1.052],[0,0],[-1.097,0],[0,0],[0,1.097],[0,0],[1.108,0],[0,0],[0,0],[0,0],[0,0.487],[0,0],[-0.487,0],[0,0],[0,0],[0,0]],"v":[[-11.14,-2.457],[-13.134,-4.34],[-14.02,-4.34],[-16.014,-2.346],[-16.014,-0.695],[-14.02,1.31],[-13.134,1.31],[-11.14,-0.695],[-11.14,-0.806],[-12.247,-0.806],[-12.247,-0.695],[-13.134,0.191],[-14.02,0.191],[-14.906,-0.695],[-14.906,-1.26],[-11.14,-1.26]],"c":true},"ix":2},"nm":"e","mn":"ADBE Vector Shape - Group","hd":false},{"ind":1,"ty":"sh","ix":2,"ks":{"a":0,"k":{"i":[[0,0],[0,0],[-0.499,0],[0,0],[0,-0.499],[0,0]],"o":[[0,0],[0,-0.487],[0,0],[0.499,0],[0,0],[0,0]],"v":[[-14.906,-2.146],[-14.906,-2.346],[-14.02,-3.232],[-13.134,-3.232],[-12.247,-2.346],[-12.247,-2.146]],"c":true},"ix":2},"nm":"e","mn":"ADBE Vector Shape - Group","hd":false},{"ty":"mm","mm":1,"nm":"Merge Paths 1","mn":"ADBE Vector Filter - Merge","hd":false},{"ty":"fl","c":{"a":0,"k":[0.161849990546,0.161849990546,0.161849990546,1],"ix":4},"o":{"a":0,"k":100,"ix":5},"r":1,"bm":0,"nm":"Fill 1","mn":"ADBE Vector Graphic - Fill","hd":false},{"ty":"tr","p":{"a":0,"k":[0,0],"ix":2},"a":{"a":0,"k":[0,0],"ix":1},"s":{"a":0,"k":[100,100],"ix":3},"r":{"a":0,"k":0,"ix":6},"o":{"a":0,"k":100,"ix":7},"sk":{"a":0,"k":0,"ix":4},"sa":{"a":0,"k":0,"ix":5},"nm":"Transform"}],"nm":"e","np":5,"cix":2,"bm":0,"ix":2,"mn":"ADBE Vector Group","hd":false},{"ty":"gr","it":[{"ind":0,"ty":"sh","ix":1,"ks":{"a":0,"k":{"i":[[0,0],[0,0],[0,0],[0,0],[0,0],[0,-1.108],[0,0],[-1.097,0],[0,0],[0,0],[0,0],[0,0]],"o":[[0,0],[0,0],[0,0],[0,0],[-1.097,0],[0,0],[0,1.097],[0,0],[0,0],[0,0],[0,0],[0,0]],"v":[[-4.54,-4.34],[-5.647,-4.34],[-5.647,-3.719],[-6.567,-4.34],[-7.42,-4.34],[-9.414,-2.346],[-9.414,-0.684],[-7.42,1.31],[-6.567,1.31],[-5.647,0.69],[-5.647,1.31],[-4.54,1.31]],"c":true},"ix":2},"nm":"a","mn":"ADBE Vector Shape - Group","hd":false},{"ind":1,"ty":"sh","ix":2,"ks":{"a":0,"k":{"i":[[0,0.487],[0,0],[-0.487,0],[0,0],[0,0],[0,0],[0,0],[0,0]],"o":[[0,0],[0,-0.487],[0,0],[0,0],[0,0],[0,0],[0,0],[-0.487,0]],"v":[[-8.306,-0.684],[-8.306,-2.346],[-7.42,-3.232],[-6.91,-3.232],[-5.647,-2.379],[-5.647,-0.651],[-6.91,0.202],[-7.42,0.202]],"c":true},"ix":2},"nm":"a","mn":"ADBE Vector Shape - Group","hd":false},{"ty":"mm","mm":1,"nm":"Merge Paths 1","mn":"ADBE Vector Filter - Merge","hd":false},{"ty":"fl","c":{"a":0,"k":[0.161849990546,0.161849990546,0.161849990546,1],"ix":4},"o":{"a":0,"k":100,"ix":5},"r":1,"bm":0,"nm":"Fill 1","mn":"ADBE Vector Graphic - Fill","hd":false},{"ty":"tr","p":{"a":0,"k":[0,0],"ix":2},"a":{"a":0,"k":[0,0],"ix":1},"s":{"a":0,"k":[100,100],"ix":3},"r":{"a":0,"k":0,"ix":6},"o":{"a":0,"k":100,"ix":7},"sk":{"a":0,"k":0,"ix":4},"sa":{"a":0,"k":0,"ix":5},"nm":"Transform"}],"nm":"a","np":5,"cix":2,"bm":0,"ix":3,"mn":"ADBE Vector Group","hd":false},{"ty":"gr","it":[{"ind":0,"ty":"sh","ix":1,"ks":{"a":0,"k":{"i":[[-1.108,0],[0,0],[0,0],[0,0],[0,0.499],[0,0],[0,0],[0,0],[0,0],[0,0],[0,0],[0,0],[0,0],[0,0],[0,0],[0,0]],"o":[[0,0],[0,0],[0,0],[-0.499,0],[0,0],[0,0],[0,0],[0,0],[0,0],[0,0],[0,0],[0,0],[0,0],[0,0],[0,0],[0,1.108]],"v":[[0.897,1.31],[2.06,1.31],[2.06,0.202],[0.897,0.202],[0.011,-0.684],[0.011,-3.232],[2.06,-3.232],[2.06,-4.34],[0.011,-4.34],[0.011,-5.78],[-1.097,-5.78],[-1.097,-4.34],[-2.814,-4.34],[-2.814,-3.232],[-1.097,-3.232],[-1.097,-0.684]],"c":true},"ix":2},"nm":"t","mn":"ADBE Vector Shape - Group","hd":false},{"ty":"fl","c":{"a":0,"k":[0.161849990546,0.161849990546,0.161849990546,1],"ix":4},"o":{"a":0,"k":100,"ix":5},"r":1,"bm":0,"nm":"Fill 1","mn":"ADBE Vector Graphic - Fill","hd":false},{"ty":"tr","p":{"a":0,"k":[0,0],"ix":2},"a":{"a":0,"k":[0,0],"ix":1},"s":{"a":0,"k":[100,100],"ix":3},"r":{"a":0,"k":0,"ix":6},"o":{"a":0,"k":100,"ix":7},"sk":{"a":0,"k":0,"ix":4},"sa":{"a":0,"k":0,"ix":5},"nm":"Transform"}],"nm":"t","np":3,"cix":2,"bm":0,"ix":4,"mn":"ADBE Vector Group","hd":false},{"ty":"gr","it":[{"ind":0,"ty":"sh","ix":1,"ks":{"a":0,"k":{"i":[[0,0],[0,0],[0,0],[0,0],[0,0],[0,0],[0,0.487],[0,0],[0,0],[0,0],[-1.097,0],[0,0],[0,0],[0,0]],"o":[[0,0],[0,0],[0,0],[0,0],[0,0],[-0.487,0],[0,0],[0,0],[0,0],[0,1.108],[0,0],[0,0],[0,0],[0,0]],"v":[[8.66,1.31],[8.66,-4.34],[7.552,-4.34],[7.552,-0.651],[6.289,0.202],[5.78,0.202],[4.894,-0.684],[4.894,-4.34],[3.786,-4.34],[3.786,-0.684],[5.78,1.31],[6.633,1.31],[7.552,0.69],[7.552,1.31]],"c":true},"ix":2},"nm":"u","mn":"ADBE Vector Shape - Group","hd":false},{"ty":"fl","c":{"a":0,"k":[0.161849990546,0.161849990546,0.161849990546,1],"ix":4},"o":{"a":0,"k":100,"ix":5},"r":1,"bm":0,"nm":"Fill 1","mn":"ADBE Vector Graphic - Fill","hd":false},{"ty":"tr","p":{"a":0,"k":[0,0],"ix":2},"a":{"a":0,"k":[0,0],"ix":1},"s":{"a":0,"k":[100,100],"ix":3},"r":{"a":0,"k":0,"ix":6},"o":{"a":0,"k":100,"ix":7},"sk":{"a":0,"k":0,"ix":4},"sa":{"a":0,"k":0,"ix":5},"nm":"Transform"}],"nm":"u","np":3,"cix":2,"bm":0,"ix":5,"mn":"ADBE Vector Group","hd":false},{"ty":"gr","it":[{"ind":0,"ty":"sh","ix":1,"ks":{"a":0,"k":{"i":[[0,0],[0,0],[0,0],[0,0],[0,0],[0,0],[0,-0.487],[0,0],[0,0],[0,0],[1.097,0],[0,0],[0,0],[0,0]],"o":[[0,0],[0,0],[0,0],[0,0],[0,0],[0.487,0],[0,0],[0,0],[0,0],[0,-1.108],[0,0],[0,0],[0,0],[0,0]],"v":[[10.386,-4.34],[10.386,1.31],[11.494,1.31],[11.494,-2.113],[13.155,-3.232],[13.266,-3.232],[14.152,-2.346],[14.152,-1.903],[15.26,-1.903],[15.26,-2.346],[13.266,-4.34],[12.812,-4.34],[11.494,-3.454],[11.494,-4.34]],"c":true},"ix":2},"nm":"r","mn":"ADBE Vector Shape - Group","hd":false},{"ty":"fl","c":{"a":0,"k":[0.161849990546,0.161849990546,0.161849990546,1],"ix":4},"o":{"a":0,"k":100,"ix":5},"r":1,"bm":0,"nm":"Fill 1","mn":"ADBE Vector Graphic - Fill","hd":false},{"ty":"tr","p":{"a":0,"k":[0,0],"ix":2},"a":{"a":0,"k":[0,0],"ix":1},"s":{"a":0,"k":[100,100],"ix":3},"r":{"a":0,"k":0,"ix":6},"o":{"a":0,"k":100,"ix":7},"sk":{"a":0,"k":0,"ix":4},"sa":{"a":0,"k":0,"ix":5},"nm":"Transform"}],"nm":"r","np":3,"cix":2,"bm":0,"ix":6,"mn":"ADBE Vector Group","hd":false},{"ty":"gr","it":[{"ind":0,"ty":"sh","ix":1,"ks":{"a":0,"k":{"i":[[0,0],[1.075,0],[0,0],[0,-1.108],[0,0],[-1.097,0],[0,0],[0,1.097],[0,0],[0,0],[0,0],[0.487,0],[0,0],[0,0.487],[0,0],[0,0]],"o":[[-0.055,-1.052],[0,0],[-1.097,0],[0,0],[0,1.097],[0,0],[1.108,0],[0,0],[0,0],[0,0],[0,0.487],[0,0],[-0.487,0],[0,0],[0,0],[0,0]],"v":[[21.86,-2.457],[19.866,-4.34],[18.98,-4.34],[16.986,-2.346],[16.986,-0.695],[18.98,1.31],[19.866,1.31],[21.86,-0.695],[21.86,-0.806],[20.752,-0.806],[20.752,-0.695],[19.866,0.191],[18.98,0.191],[18.093,-0.695],[18.093,-1.26],[21.86,-1.26]],"c":true},"ix":2},"nm":"e","mn":"ADBE Vector Shape - Group","hd":false},{"ind":1,"ty":"sh","ix":2,"ks":{"a":0,"k":{"i":[[0,0],[0,0],[-0.499,0],[0,0],[0,-0.499],[0,0]],"o":[[0,0],[0,-0.487],[0,0],[0.499,0],[0,0],[0,0]],"v":[[18.093,-2.146],[18.093,-2.346],[18.98,-3.232],[19.866,-3.232],[20.752,-2.346],[20.752,-2.146]],"c":true},"ix":2},"nm":"e","mn":"ADBE Vector Shape - Group","hd":false},{"ty":"mm","mm":1,"nm":"Merge Paths 1","mn":"ADBE Vector Filter - Merge","hd":false},{"ty":"fl","c":{"a":0,"k":[0.161849990546,0.161849990546,0.161849990546,1],"ix":4},"o":{"a":0,"k":100,"ix":5},"r":1,"bm":0,"nm":"Fill 1","mn":"ADBE Vector Graphic - Fill","hd":false},{"ty":"tr","p":{"a":0,"k":[0,0],"ix":2},"a":{"a":0,"k":[0,0],"ix":1},"s":{"a":0,"k":[100,100],"ix":3},"r":{"a":0,"k":0,"ix":6},"o":{"a":0,"k":100,"ix":7},"sk":{"a":0,"k":0,"ix":4},"sa":{"a":0,"k":0,"ix":5},"nm":"Transform"}],"nm":"e","np":5,"cix":2,"bm":0,"ix":7,"mn":"ADBE Vector Group","hd":false}],"ip":0,"op":2700,"st":0,"bm":0},{"ddd":0,"ind":2,"ty":4,"nm":"2","sr":1,"ks":{"o":{"a":1,"k":[{"i":{"x":[0.833],"y":[0.833]},"o":{"x":[0.167],"y":[0.167]},"t":120,"s":[40]},{"i":{"x":[0.833],"y":[0.833]},"o":{"x":[0.167],"y":[0.167]},"t":180,"s":[100]},{"i":{"x":[0.833],"y":[0.833]},"o":{"x":[0.167],"y":[0.167]},"t":240,"s":[100]},{"t":300,"s":[40]}],"ix":11},"r":{"a":0,"k":0,"ix":10},"p":{"a":0,"k":[1099,273,0],"ix":2,"l":2},"a":{"a":0,"k":[0,0,0],"ix":1,"l":2},"s":{"a":0,"k":[200,200,100],"ix":6,"l":2}},"ao":0,"shapes":[{"ty":"gr","it":[{"ind":0,"ty":"sh","ix":1,"ks":{"a":0,"k":{"i":[[0,0],[0,0],[0,0],[0,0],[0,0],[0,0],[0,0],[0,0],[0,0],[0,0]],"o":[[0,0],[0,0],[0,0],[0,0],[0,0],[0,0],[0,0],[0,0],[0,0],[0,0]],"v":[[-16.939,-6.445],[-21.813,-6.445],[-21.813,1.31],[-20.705,1.31],[-20.705,-1.869],[-17.382,-1.869],[-17.382,-2.977],[-20.705,-2.977],[-20.705,-5.337],[-16.939,-5.337]],"c":true},"ix":2},"nm":"F","mn":"ADBE Vector Shape - Group","hd":false},{"ty":"fl","c":{"a":0,"k":[0.161849990546,0.161849990546,0.161849990546,1],"ix":4},"o":{"a":0,"k":100,"ix":5},"r":1,"bm":0,"nm":"Fill 1","mn":"ADBE Vector Graphic - Fill","hd":false},{"ty":"tr","p":{"a":0,"k":[0,0],"ix":2},"a":{"a":0,"k":[0,0],"ix":1},"s":{"a":0,"k":[100,100],"ix":3},"r":{"a":0,"k":0,"ix":6},"o":{"a":0,"k":100,"ix":7},"sk":{"a":0,"k":0,"ix":4},"sa":{"a":0,"k":0,"ix":5},"nm":"Transform"}],"nm":"F","np":3,"cix":2,"bm":0,"ix":1,"mn":"ADBE Vector Group","hd":false},{"ty":"gr","it":[{"ind":0,"ty":"sh","ix":1,"ks":{"a":0,"k":{"i":[[0,0],[1.075,0],[0,0],[0,-1.108],[0,0],[-1.097,0],[0,0],[0,1.097],[0,0],[0,0],[0,0],[0.487,0],[0,0],[0,0.487],[0,0],[0,0]],"o":[[-0.055,-1.052],[0,0],[-1.097,0],[0,0],[0,1.097],[0,0],[1.108,0],[0,0],[0,0],[0,0],[0,0.487],[0,0],[-0.487,0],[0,0],[0,0],[0,0]],"v":[[-10.339,-2.457],[-12.333,-4.34],[-13.219,-4.34],[-15.213,-2.346],[-15.213,-0.695],[-13.219,1.31],[-12.333,1.31],[-10.339,-0.695],[-10.339,-0.806],[-11.447,-0.806],[-11.447,-0.695],[-12.333,0.191],[-13.219,0.191],[-14.105,-0.695],[-14.105,-1.26],[-10.339,-1.26]],"c":true},"ix":2},"nm":"e","mn":"ADBE Vector Shape - Group","hd":false},{"ind":1,"ty":"sh","ix":2,"ks":{"a":0,"k":{"i":[[0,0],[0,0],[-0.499,0],[0,0],[0,-0.499],[0,0]],"o":[[0,0],[0,-0.487],[0,0],[0.499,0],[0,0],[0,0]],"v":[[-14.105,-2.146],[-14.105,-2.346],[-13.219,-3.232],[-12.333,-3.232],[-11.447,-2.346],[-11.447,-2.146]],"c":true},"ix":2},"nm":"e","mn":"ADBE Vector Shape - Group","hd":false},{"ty":"mm","mm":1,"nm":"Merge Paths 1","mn":"ADBE Vector Filter - Merge","hd":false},{"ty":"fl","c":{"a":0,"k":[0.161849990546,0.161849990546,0.161849990546,1],"ix":4},"o":{"a":0,"k":100,"ix":5},"r":1,"bm":0,"nm":"Fill 1","mn":"ADBE Vector Graphic - Fill","hd":false},{"ty":"tr","p":{"a":0,"k":[0,0],"ix":2},"a":{"a":0,"k":[0,0],"ix":1},"s":{"a":0,"k":[100,100],"ix":3},"r":{"a":0,"k":0,"ix":6},"o":{"a":0,"k":100,"ix":7},"sk":{"a":0,"k":0,"ix":4},"sa":{"a":0,"k":0,"ix":5},"nm":"Transform"}],"nm":"e","np":5,"cix":2,"bm":0,"ix":2,"mn":"ADBE Vector Group","hd":false},{"ty":"gr","it":[{"ind":0,"ty":"sh","ix":1,"ks":{"a":0,"k":{"i":[[0,0],[0,0],[0,0],[0,0],[0,0],[0,-1.108],[0,0],[-1.097,0],[0,0],[0,0],[0,0],[0,0]],"o":[[0,0],[0,0],[0,0],[0,0],[-1.097,0],[0,0],[0,1.097],[0,0],[0,0],[0,0],[0,0],[0,0]],"v":[[-3.739,-4.34],[-4.847,-4.34],[-4.847,-3.719],[-5.766,-4.34],[-6.619,-4.34],[-8.613,-2.346],[-8.613,-0.684],[-6.619,1.31],[-5.766,1.31],[-4.847,0.69],[-4.847,1.31],[-3.739,1.31]],"c":true},"ix":2},"nm":"a","mn":"ADBE Vector Shape - Group","hd":false},{"ind":1,"ty":"sh","ix":2,"ks":{"a":0,"k":{"i":[[0,0.487],[0,0],[-0.487,0],[0,0],[0,0],[0,0],[0,0],[0,0]],"o":[[0,0],[0,-0.487],[0,0],[0,0],[0,0],[0,0],[0,0],[-0.487,0]],"v":[[-7.505,-0.684],[-7.505,-2.346],[-6.619,-3.232],[-6.11,-3.232],[-4.847,-2.379],[-4.847,-0.651],[-6.11,0.202],[-6.619,0.202]],"c":true},"ix":2},"nm":"a","mn":"ADBE Vector Shape - Group","hd":false},{"ty":"mm","mm":1,"nm":"Merge Paths 1","mn":"ADBE Vector Filter - Merge","hd":false},{"ty":"fl","c":{"a":0,"k":[0.161849990546,0.161849990546,0.161849990546,1],"ix":4},"o":{"a":0,"k":100,"ix":5},"r":1,"bm":0,"nm":"Fill 1","mn":"ADBE Vector Graphic - Fill","hd":false},{"ty":"tr","p":{"a":0,"k":[0,0],"ix":2},"a":{"a":0,"k":[0,0],"ix":1},"s":{"a":0,"k":[100,100],"ix":3},"r":{"a":0,"k":0,"ix":6},"o":{"a":0,"k":100,"ix":7},"sk":{"a":0,"k":0,"ix":4},"sa":{"a":0,"k":0,"ix":5},"nm":"Transform"}],"nm":"a","np":5,"cix":2,"bm":0,"ix":3,"mn":"ADBE Vector Group","hd":false},{"ty":"gr","it":[{"ind":0,"ty":"sh","ix":1,"ks":{"a":0,"k":{"i":[[-1.108,0],[0,0],[0,0],[0,0],[0,0.499],[0,0],[0,0],[0,0],[0,0],[0,0],[0,0],[0,0],[0,0],[0,0],[0,0],[0,0]],"o":[[0,0],[0,0],[0,0],[-0.499,0],[0,0],[0,0],[0,0],[0,0],[0,0],[0,0],[0,0],[0,0],[0,0],[0,0],[0,0],[0,1.108]],"v":[[1.698,1.31],[2.861,1.31],[2.861,0.202],[1.698,0.202],[0.812,-0.684],[0.812,-3.232],[2.861,-3.232],[2.861,-4.34],[0.812,-4.34],[0.812,-5.78],[-0.296,-5.78],[-0.296,-4.34],[-2.013,-4.34],[-2.013,-3.232],[-0.296,-3.232],[-0.296,-0.684]],"c":true},"ix":2},"nm":"t","mn":"ADBE Vector Shape - Group","hd":false},{"ty":"fl","c":{"a":0,"k":[0.161849990546,0.161849990546,0.161849990546,1],"ix":4},"o":{"a":0,"k":100,"ix":5},"r":1,"bm":0,"nm":"Fill 1","mn":"ADBE Vector Graphic - Fill","hd":false},{"ty":"tr","p":{"a":0,"k":[0,0],"ix":2},"a":{"a":0,"k":[0,0],"ix":1},"s":{"a":0,"k":[100,100],"ix":3},"r":{"a":0,"k":0,"ix":6},"o":{"a":0,"k":100,"ix":7},"sk":{"a":0,"k":0,"ix":4},"sa":{"a":0,"k":0,"ix":5},"nm":"Transform"}],"nm":"t","np":3,"cix":2,"bm":0,"ix":4,"mn":"ADBE Vector Group","hd":false},{"ty":"gr","it":[{"ind":0,"ty":"sh","ix":1,"ks":{"a":0,"k":{"i":[[0,0],[0,0],[0,0],[0,0],[0,0],[0,0],[0,0.487],[0,0],[0,0],[0,0],[-1.097,0],[0,0],[0,0],[0,0]],"o":[[0,0],[0,0],[0,0],[0,0],[0,0],[-0.487,0],[0,0],[0,0],[0,0],[0,1.108],[0,0],[0,0],[0,0],[0,0]],"v":[[9.461,1.31],[9.461,-4.34],[8.353,-4.34],[8.353,-0.651],[7.09,0.202],[6.581,0.202],[5.694,-0.684],[5.694,-4.34],[4.587,-4.34],[4.587,-0.684],[6.581,1.31],[7.434,1.31],[8.353,0.69],[8.353,1.31]],"c":true},"ix":2},"nm":"u","mn":"ADBE Vector Shape - Group","hd":false},{"ty":"fl","c":{"a":0,"k":[0.161849990546,0.161849990546,0.161849990546,1],"ix":4},"o":{"a":0,"k":100,"ix":5},"r":1,"bm":0,"nm":"Fill 1","mn":"ADBE Vector Graphic - Fill","hd":false},{"ty":"tr","p":{"a":0,"k":[0,0],"ix":2},"a":{"a":0,"k":[0,0],"ix":1},"s":{"a":0,"k":[100,100],"ix":3},"r":{"a":0,"k":0,"ix":6},"o":{"a":0,"k":100,"ix":7},"sk":{"a":0,"k":0,"ix":4},"sa":{"a":0,"k":0,"ix":5},"nm":"Transform"}],"nm":"u","np":3,"cix":2,"bm":0,"ix":5,"mn":"ADBE Vector Group","hd":false},{"ty":"gr","it":[{"ind":0,"ty":"sh","ix":1,"ks":{"a":0,"k":{"i":[[0,0],[0,0],[0,0],[0,0],[0,0],[0,0],[0,-0.487],[0,0],[0,0],[0,0],[1.097,0],[0,0],[0,0],[0,0]],"o":[[0,0],[0,0],[0,0],[0,0],[0,0],[0.487,0],[0,0],[0,0],[0,0],[0,-1.108],[0,0],[0,0],[0,0],[0,0]],"v":[[11.187,-4.34],[11.187,1.31],[12.294,1.31],[12.294,-2.113],[13.956,-3.232],[14.067,-3.232],[14.953,-2.346],[14.953,-1.903],[16.061,-1.903],[16.061,-2.346],[14.067,-4.34],[13.613,-4.34],[12.294,-3.454],[12.294,-4.34]],"c":true},"ix":2},"nm":"r","mn":"ADBE Vector Shape - Group","hd":false},{"ty":"fl","c":{"a":0,"k":[0.161849990546,0.161849990546,0.161849990546,1],"ix":4},"o":{"a":0,"k":100,"ix":5},"r":1,"bm":0,"nm":"Fill 1","mn":"ADBE Vector Graphic - Fill","hd":false},{"ty":"tr","p":{"a":0,"k":[0,0],"ix":2},"a":{"a":0,"k":[0,0],"ix":1},"s":{"a":0,"k":[100,100],"ix":3},"r":{"a":0,"k":0,"ix":6},"o":{"a":0,"k":100,"ix":7},"sk":{"a":0,"k":0,"ix":4},"sa":{"a":0,"k":0,"ix":5},"nm":"Transform"}],"nm":"r","np":3,"cix":2,"bm":0,"ix":6,"mn":"ADBE Vector Group","hd":false},{"ty":"gr","it":[{"ind":0,"ty":"sh","ix":1,"ks":{"a":0,"k":{"i":[[0,0],[1.075,0],[0,0],[0,-1.108],[0,0],[-1.097,0],[0,0],[0,1.097],[0,0],[0,0],[0,0],[0.487,0],[0,0],[0,0.487],[0,0],[0,0]],"o":[[-0.055,-1.052],[0,0],[-1.097,0],[0,0],[0,1.097],[0,0],[1.108,0],[0,0],[0,0],[0,0],[0,0.487],[0,0],[-0.487,0],[0,0],[0,0],[0,0]],"v":[[22.661,-2.457],[20.667,-4.34],[19.78,-4.34],[17.786,-2.346],[17.786,-0.695],[19.78,1.31],[20.667,1.31],[22.661,-0.695],[22.661,-0.806],[21.553,-0.806],[21.553,-0.695],[20.667,0.191],[19.78,0.191],[18.894,-0.695],[18.894,-1.26],[22.661,-1.26]],"c":true},"ix":2},"nm":"e","mn":"ADBE Vector Shape - Group","hd":false},{"ind":1,"ty":"sh","ix":2,"ks":{"a":0,"k":{"i":[[0,0],[0,0],[-0.499,0],[0,0],[0,-0.499],[0,0]],"o":[[0,0],[0,-0.487],[0,0],[0.499,0],[0,0],[0,0]],"v":[[18.894,-2.146],[18.894,-2.346],[19.78,-3.232],[20.667,-3.232],[21.553,-2.346],[21.553,-2.146]],"c":true},"ix":2},"nm":"e","mn":"ADBE Vector Shape - Group","hd":false},{"ty":"mm","mm":1,"nm":"Merge Paths 1","mn":"ADBE Vector Filter - Merge","hd":false},{"ty":"fl","c":{"a":0,"k":[0.161849990546,0.161849990546,0.161849990546,1],"ix":4},"o":{"a":0,"k":100,"ix":5},"r":1,"bm":0,"nm":"Fill 1","mn":"ADBE Vector Graphic - Fill","hd":false},{"ty":"tr","p":{"a":0,"k":[0,0],"ix":2},"a":{"a":0,"k":[0,0],"ix":1},"s":{"a":0,"k":[100,100],"ix":3},"r":{"a":0,"k":0,"ix":6},"o":{"a":0,"k":100,"ix":7},"sk":{"a":0,"k":0,"ix":4},"sa":{"a":0,"k":0,"ix":5},"nm":"Transform"}],"nm":"e","np":5,"cix":2,"bm":0,"ix":7,"mn":"ADBE Vector Group","hd":false}],"ip":0,"op":2700,"st":0,"bm":0},{"ddd":0,"ind":3,"ty":4,"nm":"3","sr":1,"ks":{"o":{"a":1,"k":[{"i":{"x":[0.833],"y":[0.833]},"o":{"x":[0.167],"y":[0.167]},"t":300,"s":[40]},{"i":{"x":[0.833],"y":[0.833]},"o":{"x":[0.167],"y":[0.167]},"t":360,"s":[100]},{"i":{"x":[0.833],"y":[0.833]},"o":{"x":[0.167],"y":[0.167]},"t":420,"s":[100]},{"t":480,"s":[40]}],"ix":11},"r":{"a":0,"k":0,"ix":10},"p":{"a":0,"k":[339,1185,0],"ix":2,"l":2},"a":{"a":0,"k":[0,0,0],"ix":1,"l":2},"s":{"a":0,"k":[200,200,100],"ix":6,"l":2}},"ao":0,"shapes":[{"ty":"gr","it":[{"ind":0,"ty":"sh","ix":1,"ks":{"a":0,"k":{"i":[[0,0],[0,0],[0,0],[0,0],[0,0],[0,0],[0,0],[0,0],[0,0],[0,0]],"o":[[0,0],[0,0],[0,0],[0,0],[0,0],[0,0],[0,0],[0,0],[0,0],[0,0]],"v":[[-17.74,-6.445],[-22.614,-6.445],[-22.614,1.31],[-21.506,1.31],[-21.506,-1.869],[-18.183,-1.869],[-18.183,-2.977],[-21.506,-2.977],[-21.506,-5.337],[-17.74,-5.337]],"c":true},"ix":2},"nm":"F","mn":"ADBE Vector Shape - Group","hd":false},{"ty":"fl","c":{"a":0,"k":[0.161849990546,0.161849990546,0.161849990546,1],"ix":4},"o":{"a":0,"k":100,"ix":5},"r":1,"bm":0,"nm":"Fill 1","mn":"ADBE Vector Graphic - Fill","hd":false},{"ty":"tr","p":{"a":0,"k":[0,0],"ix":2},"a":{"a":0,"k":[0,0],"ix":1},"s":{"a":0,"k":[100,100],"ix":3},"r":{"a":0,"k":0,"ix":6},"o":{"a":0,"k":100,"ix":7},"sk":{"a":0,"k":0,"ix":4},"sa":{"a":0,"k":0,"ix":5},"nm":"Transform"}],"nm":"F","np":3,"cix":2,"bm":0,"ix":1,"mn":"ADBE Vector Group","hd":false},{"ty":"gr","it":[{"ind":0,"ty":"sh","ix":1,"ks":{"a":0,"k":{"i":[[0,0],[1.075,0],[0,0],[0,-1.108],[0,0],[-1.097,0],[0,0],[0,1.097],[0,0],[0,0],[0,0],[0.487,0],[0,0],[0,0.487],[0,0],[0,0]],"o":[[-0.055,-1.052],[0,0],[-1.097,0],[0,0],[0,1.097],[0,0],[1.108,0],[0,0],[0,0],[0,0],[0,0.487],[0,0],[-0.487,0],[0,0],[0,0],[0,0]],"v":[[-11.14,-2.457],[-13.134,-4.34],[-14.02,-4.34],[-16.014,-2.346],[-16.014,-0.695],[-14.02,1.31],[-13.134,1.31],[-11.14,-0.695],[-11.14,-0.806],[-12.247,-0.806],[-12.247,-0.695],[-13.134,0.191],[-14.02,0.191],[-14.906,-0.695],[-14.906,-1.26],[-11.14,-1.26]],"c":true},"ix":2},"nm":"e","mn":"ADBE Vector Shape - Group","hd":false},{"ind":1,"ty":"sh","ix":2,"ks":{"a":0,"k":{"i":[[0,0],[0,0],[-0.499,0],[0,0],[0,-0.499],[0,0]],"o":[[0,0],[0,-0.487],[0,0],[0.499,0],[0,0],[0,0]],"v":[[-14.906,-2.146],[-14.906,-2.346],[-14.02,-3.232],[-13.134,-3.232],[-12.247,-2.346],[-12.247,-2.146]],"c":true},"ix":2},"nm":"e","mn":"ADBE Vector Shape - Group","hd":false},{"ty":"mm","mm":1,"nm":"Merge Paths 1","mn":"ADBE Vector Filter - Merge","hd":false},{"ty":"fl","c":{"a":0,"k":[0.161849990546,0.161849990546,0.161849990546,1],"ix":4},"o":{"a":0,"k":100,"ix":5},"r":1,"bm":0,"nm":"Fill 1","mn":"ADBE Vector Graphic - Fill","hd":false},{"ty":"tr","p":{"a":0,"k":[0,0],"ix":2},"a":{"a":0,"k":[0,0],"ix":1},"s":{"a":0,"k":[100,100],"ix":3},"r":{"a":0,"k":0,"ix":6},"o":{"a":0,"k":100,"ix":7},"sk":{"a":0,"k":0,"ix":4},"sa":{"a":0,"k":0,"ix":5},"nm":"Transform"}],"nm":"e","np":5,"cix":2,"bm":0,"ix":2,"mn":"ADBE Vector Group","hd":false},{"ty":"gr","it":[{"ind":0,"ty":"sh","ix":1,"ks":{"a":0,"k":{"i":[[0,0],[0,0],[0,0],[0,0],[0,0],[0,-1.108],[0,0],[-1.097,0],[0,0],[0,0],[0,0],[0,0]],"o":[[0,0],[0,0],[0,0],[0,0],[-1.097,0],[0,0],[0,1.097],[0,0],[0,0],[0,0],[0,0],[0,0]],"v":[[-4.54,-4.34],[-5.647,-4.34],[-5.647,-3.719],[-6.567,-4.34],[-7.42,-4.34],[-9.414,-2.346],[-9.414,-0.684],[-7.42,1.31],[-6.567,1.31],[-5.647,0.69],[-5.647,1.31],[-4.54,1.31]],"c":true},"ix":2},"nm":"a","mn":"ADBE Vector Shape - Group","hd":false},{"ind":1,"ty":"sh","ix":2,"ks":{"a":0,"k":{"i":[[0,0.487],[0,0],[-0.487,0],[0,0],[0,0],[0,0],[0,0],[0,0]],"o":[[0,0],[0,-0.487],[0,0],[0,0],[0,0],[0,0],[0,0],[-0.487,0]],"v":[[-8.306,-0.684],[-8.306,-2.346],[-7.42,-3.232],[-6.91,-3.232],[-5.647,-2.379],[-5.647,-0.651],[-6.91,0.202],[-7.42,0.202]],"c":true},"ix":2},"nm":"a","mn":"ADBE Vector Shape - Group","hd":false},{"ty":"mm","mm":1,"nm":"Merge Paths 1","mn":"ADBE Vector Filter - Merge","hd":false},{"ty":"fl","c":{"a":0,"k":[0.161849990546,0.161849990546,0.161849990546,1],"ix":4},"o":{"a":0,"k":100,"ix":5},"r":1,"bm":0,"nm":"Fill 1","mn":"ADBE Vector Graphic - Fill","hd":false},{"ty":"tr","p":{"a":0,"k":[0,0],"ix":2},"a":{"a":0,"k":[0,0],"ix":1},"s":{"a":0,"k":[100,100],"ix":3},"r":{"a":0,"k":0,"ix":6},"o":{"a":0,"k":100,"ix":7},"sk":{"a":0,"k":0,"ix":4},"sa":{"a":0,"k":0,"ix":5},"nm":"Transform"}],"nm":"a","np":5,"cix":2,"bm":0,"ix":3,"mn":"ADBE Vector Group","hd":false},{"ty":"gr","it":[{"ind":0,"ty":"sh","ix":1,"ks":{"a":0,"k":{"i":[[-1.108,0],[0,0],[0,0],[0,0],[0,0.499],[0,0],[0,0],[0,0],[0,0],[0,0],[0,0],[0,0],[0,0],[0,0],[0,0],[0,0]],"o":[[0,0],[0,0],[0,0],[-0.499,0],[0,0],[0,0],[0,0],[0,0],[0,0],[0,0],[0,0],[0,0],[0,0],[0,0],[0,0],[0,1.108]],"v":[[0.897,1.31],[2.06,1.31],[2.06,0.202],[0.897,0.202],[0.011,-0.684],[0.011,-3.232],[2.06,-3.232],[2.06,-4.34],[0.011,-4.34],[0.011,-5.78],[-1.097,-5.78],[-1.097,-4.34],[-2.814,-4.34],[-2.814,-3.232],[-1.097,-3.232],[-1.097,-0.684]],"c":true},"ix":2},"nm":"t","mn":"ADBE Vector Shape - Group","hd":false},{"ty":"fl","c":{"a":0,"k":[0.161849990546,0.161849990546,0.161849990546,1],"ix":4},"o":{"a":0,"k":100,"ix":5},"r":1,"bm":0,"nm":"Fill 1","mn":"ADBE Vector Graphic - Fill","hd":false},{"ty":"tr","p":{"a":0,"k":[0,0],"ix":2},"a":{"a":0,"k":[0,0],"ix":1},"s":{"a":0,"k":[100,100],"ix":3},"r":{"a":0,"k":0,"ix":6},"o":{"a":0,"k":100,"ix":7},"sk":{"a":0,"k":0,"ix":4},"sa":{"a":0,"k":0,"ix":5},"nm":"Transform"}],"nm":"t","np":3,"cix":2,"bm":0,"ix":4,"mn":"ADBE Vector Group","hd":false},{"ty":"gr","it":[{"ind":0,"ty":"sh","ix":1,"ks":{"a":0,"k":{"i":[[0,0],[0,0],[0,0],[0,0],[0,0],[0,0],[0,0.487],[0,0],[0,0],[0,0],[-1.097,0],[0,0],[0,0],[0,0]],"o":[[0,0],[0,0],[0,0],[0,0],[0,0],[-0.487,0],[0,0],[0,0],[0,0],[0,1.108],[0,0],[0,0],[0,0],[0,0]],"v":[[8.66,1.31],[8.66,-4.34],[7.552,-4.34],[7.552,-0.651],[6.289,0.202],[5.78,0.202],[4.894,-0.684],[4.894,-4.34],[3.786,-4.34],[3.786,-0.684],[5.78,1.31],[6.633,1.31],[7.552,0.69],[7.552,1.31]],"c":true},"ix":2},"nm":"u","mn":"ADBE Vector Shape - Group","hd":false},{"ty":"fl","c":{"a":0,"k":[0.161849990546,0.161849990546,0.161849990546,1],"ix":4},"o":{"a":0,"k":100,"ix":5},"r":1,"bm":0,"nm":"Fill 1","mn":"ADBE Vector Graphic - Fill","hd":false},{"ty":"tr","p":{"a":0,"k":[0,0],"ix":2},"a":{"a":0,"k":[0,0],"ix":1},"s":{"a":0,"k":[100,100],"ix":3},"r":{"a":0,"k":0,"ix":6},"o":{"a":0,"k":100,"ix":7},"sk":{"a":0,"k":0,"ix":4},"sa":{"a":0,"k":0,"ix":5},"nm":"Transform"}],"nm":"u","np":3,"cix":2,"bm":0,"ix":5,"mn":"ADBE Vector Group","hd":false},{"ty":"gr","it":[{"ind":0,"ty":"sh","ix":1,"ks":{"a":0,"k":{"i":[[0,0],[0,0],[0,0],[0,0],[0,0],[0,0],[0,-0.487],[0,0],[0,0],[0,0],[1.097,0],[0,0],[0,0],[0,0]],"o":[[0,0],[0,0],[0,0],[0,0],[0,0],[0.487,0],[0,0],[0,0],[0,0],[0,-1.108],[0,0],[0,0],[0,0],[0,0]],"v":[[10.386,-4.34],[10.386,1.31],[11.494,1.31],[11.494,-2.113],[13.155,-3.232],[13.266,-3.232],[14.152,-2.346],[14.152,-1.903],[15.26,-1.903],[15.26,-2.346],[13.266,-4.34],[12.812,-4.34],[11.494,-3.454],[11.494,-4.34]],"c":true},"ix":2},"nm":"r","mn":"ADBE Vector Shape - Group","hd":false},{"ty":"fl","c":{"a":0,"k":[0.161849990546,0.161849990546,0.161849990546,1],"ix":4},"o":{"a":0,"k":100,"ix":5},"r":1,"bm":0,"nm":"Fill 1","mn":"ADBE Vector Graphic - Fill","hd":false},{"ty":"tr","p":{"a":0,"k":[0,0],"ix":2},"a":{"a":0,"k":[0,0],"ix":1},"s":{"a":0,"k":[100,100],"ix":3},"r":{"a":0,"k":0,"ix":6},"o":{"a":0,"k":100,"ix":7},"sk":{"a":0,"k":0,"ix":4},"sa":{"a":0,"k":0,"ix":5},"nm":"Transform"}],"nm":"r","np":3,"cix":2,"bm":0,"ix":6,"mn":"ADBE Vector Group","hd":false},{"ty":"gr","it":[{"ind":0,"ty":"sh","ix":1,"ks":{"a":0,"k":{"i":[[0,0],[1.075,0],[0,0],[0,-1.108],[0,0],[-1.097,0],[0,0],[0,1.097],[0,0],[0,0],[0,0],[0.487,0],[0,0],[0,0.487],[0,0],[0,0]],"o":[[-0.055,-1.052],[0,0],[-1.097,0],[0,0],[0,1.097],[0,0],[1.108,0],[0,0],[0,0],[0,0],[0,0.487],[0,0],[-0.487,0],[0,0],[0,0],[0,0]],"v":[[21.86,-2.457],[19.866,-4.34],[18.98,-4.34],[16.986,-2.346],[16.986,-0.695],[18.98,1.31],[19.866,1.31],[21.86,-0.695],[21.86,-0.806],[20.752,-0.806],[20.752,-0.695],[19.866,0.191],[18.98,0.191],[18.093,-0.695],[18.093,-1.26],[21.86,-1.26]],"c":true},"ix":2},"nm":"e","mn":"ADBE Vector Shape - Group","hd":false},{"ind":1,"ty":"sh","ix":2,"ks":{"a":0,"k":{"i":[[0,0],[0,0],[-0.499,0],[0,0],[0,-0.499],[0,0]],"o":[[0,0],[0,-0.487],[0,0],[0.499,0],[0,0],[0,0]],"v":[[18.093,-2.146],[18.093,-2.346],[18.98,-3.232],[19.866,-3.232],[20.752,-2.346],[20.752,-2.146]],"c":true},"ix":2},"nm":"e","mn":"ADBE Vector Shape - Group","hd":false},{"ty":"mm","mm":1,"nm":"Merge Paths 1","mn":"ADBE Vector Filter - Merge","hd":false},{"ty":"fl","c":{"a":0,"k":[0.161849990546,0.161849990546,0.161849990546,1],"ix":4},"o":{"a":0,"k":100,"ix":5},"r":1,"bm":0,"nm":"Fill 1","mn":"ADBE Vector Graphic - Fill","hd":false},{"ty":"tr","p":{"a":0,"k":[0,0],"ix":2},"a":{"a":0,"k":[0,0],"ix":1},"s":{"a":0,"k":[100,100],"ix":3},"r":{"a":0,"k":0,"ix":6},"o":{"a":0,"k":100,"ix":7},"sk":{"a":0,"k":0,"ix":4},"sa":{"a":0,"k":0,"ix":5},"nm":"Transform"}],"nm":"e","np":5,"cix":2,"bm":0,"ix":7,"mn":"ADBE Vector Group","hd":false}],"ip":0,"op":2700,"st":0,"bm":0},{"ddd":0,"ind":4,"ty":4,"nm":"4","sr":1,"ks":{"o":{"a":1,"k":[{"i":{"x":[0.833],"y":[0.833]},"o":{"x":[0.167],"y":[0.167]},"t":480,"s":[40]},{"t":540,"s":[100]}],"ix":11},"r":{"a":0,"k":0,"ix":10},"p":{"a":0,"k":[1099,1185,0],"ix":2,"l":2},"a":{"a":0,"k":[0,0,0],"ix":1,"l":2},"s":{"a":0,"k":[200,200,100],"ix":6,"l":2}},"ao":0,"shapes":[{"ty":"gr","it":[{"ind":0,"ty":"sh","ix":1,"ks":{"a":0,"k":{"i":[[0,0],[0,0],[0,0],[0,0],[0,0],[0,0],[0,0],[0,0],[0,0],[0,0]],"o":[[0,0],[0,0],[0,0],[0,0],[0,0],[0,0],[0,0],[0,0],[0,0],[0,0]],"v":[[-16.939,-6.445],[-21.813,-6.445],[-21.813,1.31],[-20.705,1.31],[-20.705,-1.869],[-17.382,-1.869],[-17.382,-2.977],[-20.705,-2.977],[-20.705,-5.337],[-16.939,-5.337]],"c":true},"ix":2},"nm":"F","mn":"ADBE Vector Shape - Group","hd":false},{"ty":"fl","c":{"a":0,"k":[0.161849990546,0.161849990546,0.161849990546,1],"ix":4},"o":{"a":0,"k":100,"ix":5},"r":1,"bm":0,"nm":"Fill 1","mn":"ADBE Vector Graphic - Fill","hd":false},{"ty":"tr","p":{"a":0,"k":[0,0],"ix":2},"a":{"a":0,"k":[0,0],"ix":1},"s":{"a":0,"k":[100,100],"ix":3},"r":{"a":0,"k":0,"ix":6},"o":{"a":0,"k":100,"ix":7},"sk":{"a":0,"k":0,"ix":4},"sa":{"a":0,"k":0,"ix":5},"nm":"Transform"}],"nm":"F","np":3,"cix":2,"bm":0,"ix":1,"mn":"ADBE Vector Group","hd":false},{"ty":"gr","it":[{"ind":0,"ty":"sh","ix":1,"ks":{"a":0,"k":{"i":[[0,0],[1.075,0],[0,0],[0,-1.108],[0,0],[-1.097,0],[0,0],[0,1.097],[0,0],[0,0],[0,0],[0.487,0],[0,0],[0,0.487],[0,0],[0,0]],"o":[[-0.055,-1.052],[0,0],[-1.097,0],[0,0],[0,1.097],[0,0],[1.108,0],[0,0],[0,0],[0,0],[0,0.487],[0,0],[-0.487,0],[0,0],[0,0],[0,0]],"v":[[-10.339,-2.457],[-12.333,-4.34],[-13.219,-4.34],[-15.213,-2.346],[-15.213,-0.695],[-13.219,1.31],[-12.333,1.31],[-10.339,-0.695],[-10.339,-0.806],[-11.447,-0.806],[-11.447,-0.695],[-12.333,0.191],[-13.219,0.191],[-14.105,-0.695],[-14.105,-1.26],[-10.339,-1.26]],"c":true},"ix":2},"nm":"e","mn":"ADBE Vector Shape - Group","hd":false},{"ind":1,"ty":"sh","ix":2,"ks":{"a":0,"k":{"i":[[0,0],[0,0],[-0.499,0],[0,0],[0,-0.499],[0,0]],"o":[[0,0],[0,-0.487],[0,0],[0.499,0],[0,0],[0,0]],"v":[[-14.105,-2.146],[-14.105,-2.346],[-13.219,-3.232],[-12.333,-3.232],[-11.447,-2.346],[-11.447,-2.146]],"c":true},"ix":2},"nm":"e","mn":"ADBE Vector Shape - Group","hd":false},{"ty":"mm","mm":1,"nm":"Merge Paths 1","mn":"ADBE Vector Filter - Merge","hd":false},{"ty":"fl","c":{"a":0,"k":[0.161849990546,0.161849990546,0.161849990546,1],"ix":4},"o":{"a":0,"k":100,"ix":5},"r":1,"bm":0,"nm":"Fill 1","mn":"ADBE Vector Graphic - Fill","hd":false},{"ty":"tr","p":{"a":0,"k":[0,0],"ix":2},"a":{"a":0,"k":[0,0],"ix":1},"s":{"a":0,"k":[100,100],"ix":3},"r":{"a":0,"k":0,"ix":6},"o":{"a":0,"k":100,"ix":7},"sk":{"a":0,"k":0,"ix":4},"sa":{"a":0,"k":0,"ix":5},"nm":"Transform"}],"nm":"e","np":5,"cix":2,"bm":0,"ix":2,"mn":"ADBE Vector Group","hd":false},{"ty":"gr","it":[{"ind":0,"ty":"sh","ix":1,"ks":{"a":0,"k":{"i":[[0,0],[0,0],[0,0],[0,0],[0,0],[0,-1.108],[0,0],[-1.097,0],[0,0],[0,0],[0,0],[0,0]],"o":[[0,0],[0,0],[0,0],[0,0],[-1.097,0],[0,0],[0,1.097],[0,0],[0,0],[0,0],[0,0],[0,0]],"v":[[-3.739,-4.34],[-4.847,-4.34],[-4.847,-3.719],[-5.766,-4.34],[-6.619,-4.34],[-8.613,-2.346],[-8.613,-0.684],[-6.619,1.31],[-5.766,1.31],[-4.847,0.69],[-4.847,1.31],[-3.739,1.31]],"c":true},"ix":2},"nm":"a","mn":"ADBE Vector Shape - Group","hd":false},{"ind":1,"ty":"sh","ix":2,"ks":{"a":0,"k":{"i":[[0,0.487],[0,0],[-0.487,0],[0,0],[0,0],[0,0],[0,0],[0,0]],"o":[[0,0],[0,-0.487],[0,0],[0,0],[0,0],[0,0],[0,0],[-0.487,0]],"v":[[-7.505,-0.684],[-7.505,-2.346],[-6.619,-3.232],[-6.11,-3.232],[-4.847,-2.379],[-4.847,-0.651],[-6.11,0.202],[-6.619,0.202]],"c":true},"ix":2},"nm":"a","mn":"ADBE Vector Shape - Group","hd":false},{"ty":"mm","mm":1,"nm":"Merge Paths 1","mn":"ADBE Vector Filter - Merge","hd":false},{"ty":"fl","c":{"a":0,"k":[0.161849990546,0.161849990546,0.161849990546,1],"ix":4},"o":{"a":0,"k":100,"ix":5},"r":1,"bm":0,"nm":"Fill 1","mn":"ADBE Vector Graphic - Fill","hd":false},{"ty":"tr","p":{"a":0,"k":[0,0],"ix":2},"a":{"a":0,"k":[0,0],"ix":1},"s":{"a":0,"k":[100,100],"ix":3},"r":{"a":0,"k":0,"ix":6},"o":{"a":0,"k":100,"ix":7},"sk":{"a":0,"k":0,"ix":4},"sa":{"a":0,"k":0,"ix":5},"nm":"Transform"}],"nm":"a","np":5,"cix":2,"bm":0,"ix":3,"mn":"ADBE Vector Group","hd":false},{"ty":"gr","it":[{"ind":0,"ty":"sh","ix":1,"ks":{"a":0,"k":{"i":[[-1.108,0],[0,0],[0,0],[0,0],[0,0.499],[0,0],[0,0],[0,0],[0,0],[0,0],[0,0],[0,0],[0,0],[0,0],[0,0],[0,0]],"o":[[0,0],[0,0],[0,0],[-0.499,0],[0,0],[0,0],[0,0],[0,0],[0,0],[0,0],[0,0],[0,0],[0,0],[0,0],[0,0],[0,1.108]],"v":[[1.698,1.31],[2.861,1.31],[2.861,0.202],[1.698,0.202],[0.812,-0.684],[0.812,-3.232],[2.861,-3.232],[2.861,-4.34],[0.812,-4.34],[0.812,-5.78],[-0.296,-5.78],[-0.296,-4.34],[-2.013,-4.34],[-2.013,-3.232],[-0.296,-3.232],[-0.296,-0.684]],"c":true},"ix":2},"nm":"t","mn":"ADBE Vector Shape - Group","hd":false},{"ty":"fl","c":{"a":0,"k":[0.161849990546,0.161849990546,0.161849990546,1],"ix":4},"o":{"a":0,"k":100,"ix":5},"r":1,"bm":0,"nm":"Fill 1","mn":"ADBE Vector Graphic - Fill","hd":false},{"ty":"tr","p":{"a":0,"k":[0,0],"ix":2},"a":{"a":0,"k":[0,0],"ix":1},"s":{"a":0,"k":[100,100],"ix":3},"r":{"a":0,"k":0,"ix":6},"o":{"a":0,"k":100,"ix":7},"sk":{"a":0,"k":0,"ix":4},"sa":{"a":0,"k":0,"ix":5},"nm":"Transform"}],"nm":"t","np":3,"cix":2,"bm":0,"ix":4,"mn":"ADBE Vector Group","hd":false},{"ty":"gr","it":[{"ind":0,"ty":"sh","ix":1,"ks":{"a":0,"k":{"i":[[0,0],[0,0],[0,0],[0,0],[0,0],[0,0],[0,0.487],[0,0],[0,0],[0,0],[-1.097,0],[0,0],[0,0],[0,0]],"o":[[0,0],[0,0],[0,0],[0,0],[0,0],[-0.487,0],[0,0],[0,0],[0,0],[0,1.108],[0,0],[0,0],[0,0],[0,0]],"v":[[9.461,1.31],[9.461,-4.34],[8.353,-4.34],[8.353,-0.651],[7.09,0.202],[6.581,0.202],[5.694,-0.684],[5.694,-4.34],[4.587,-4.34],[4.587,-0.684],[6.581,1.31],[7.434,1.31],[8.353,0.69],[8.353,1.31]],"c":true},"ix":2},"nm":"u","mn":"ADBE Vector Shape - Group","hd":false},{"ty":"fl","c":{"a":0,"k":[0.161849990546,0.161849990546,0.161849990546,1],"ix":4},"o":{"a":0,"k":100,"ix":5},"r":1,"bm":0,"nm":"Fill 1","mn":"ADBE Vector Graphic - Fill","hd":false},{"ty":"tr","p":{"a":0,"k":[0,0],"ix":2},"a":{"a":0,"k":[0,0],"ix":1},"s":{"a":0,"k":[100,100],"ix":3},"r":{"a":0,"k":0,"ix":6},"o":{"a":0,"k":100,"ix":7},"sk":{"a":0,"k":0,"ix":4},"sa":{"a":0,"k":0,"ix":5},"nm":"Transform"}],"nm":"u","np":3,"cix":2,"bm":0,"ix":5,"mn":"ADBE Vector Group","hd":false},{"ty":"gr","it":[{"ind":0,"ty":"sh","ix":1,"ks":{"a":0,"k":{"i":[[0,0],[0,0],[0,0],[0,0],[0,0],[0,0],[0,-0.487],[0,0],[0,0],[0,0],[1.097,0],[0,0],[0,0],[0,0]],"o":[[0,0],[0,0],[0,0],[0,0],[0,0],[0.487,0],[0,0],[0,0],[0,0],[0,-1.108],[0,0],[0,0],[0,0],[0,0]],"v":[[11.187,-4.34],[11.187,1.31],[12.294,1.31],[12.294,-2.113],[13.956,-3.232],[14.067,-3.232],[14.953,-2.346],[14.953,-1.903],[16.061,-1.903],[16.061,-2.346],[14.067,-4.34],[13.613,-4.34],[12.294,-3.454],[12.294,-4.34]],"c":true},"ix":2},"nm":"r","mn":"ADBE Vector Shape - Group","hd":false},{"ty":"fl","c":{"a":0,"k":[0.161849990546,0.161849990546,0.161849990546,1],"ix":4},"o":{"a":0,"k":100,"ix":5},"r":1,"bm":0,"nm":"Fill 1","mn":"ADBE Vector Graphic - Fill","hd":false},{"ty":"tr","p":{"a":0,"k":[0,0],"ix":2},"a":{"a":0,"k":[0,0],"ix":1},"s":{"a":0,"k":[100,100],"ix":3},"r":{"a":0,"k":0,"ix":6},"o":{"a":0,"k":100,"ix":7},"sk":{"a":0,"k":0,"ix":4},"sa":{"a":0,"k":0,"ix":5},"nm":"Transform"}],"nm":"r","np":3,"cix":2,"bm":0,"ix":6,"mn":"ADBE Vector Group","hd":false},{"ty":"gr","it":[{"ind":0,"ty":"sh","ix":1,"ks":{"a":0,"k":{"i":[[0,0],[1.075,0],[0,0],[0,-1.108],[0,0],[-1.097,0],[0,0],[0,1.097],[0,0],[0,0],[0,0],[0.487,0],[0,0],[0,0.487],[0,0],[0,0]],"o":[[-0.055,-1.052],[0,0],[-1.097,0],[0,0],[0,1.097],[0,0],[1.108,0],[0,0],[0,0],[0,0],[0,0.487],[0,0],[-0.487,0],[0,0],[0,0],[0,0]],"v":[[22.661,-2.457],[20.667,-4.34],[19.78,-4.34],[17.786,-2.346],[17.786,-0.695],[19.78,1.31],[20.667,1.31],[22.661,-0.695],[22.661,-0.806],[21.553,-0.806],[21.553,-0.695],[20.667,0.191],[19.78,0.191],[18.894,-0.695],[18.894,-1.26],[22.661,-1.26]],"c":true},"ix":2},"nm":"e","mn":"ADBE Vector Shape - Group","hd":false},{"ind":1,"ty":"sh","ix":2,"ks":{"a":0,"k":{"i":[[0,0],[0,0],[-0.499,0],[0,0],[0,-0.499],[0,0]],"o":[[0,0],[0,-0.487],[0,0],[0.499,0],[0,0],[0,0]],"v":[[18.894,-2.146],[18.894,-2.346],[19.78,-3.232],[20.667,-3.232],[21.553,-2.346],[21.553,-2.146]],"c":true},"ix":2},"nm":"e","mn":"ADBE Vector Shape - Group","hd":false},{"ty":"mm","mm":1,"nm":"Merge Paths 1","mn":"ADBE Vector Filter - Merge","hd":false},{"ty":"fl","c":{"a":0,"k":[0.161849990546,0.161849990546,0.161849990546,1],"ix":4},"o":{"a":0,"k":100,"ix":5},"r":1,"bm":0,"nm":"Fill 1","mn":"ADBE Vector Graphic - Fill","hd":false},{"ty":"tr","p":{"a":0,"k":[0,0],"ix":2},"a":{"a":0,"k":[0,0],"ix":1},"s":{"a":0,"k":[100,100],"ix":3},"r":{"a":0,"k":0,"ix":6},"o":{"a":0,"k":100,"ix":7},"sk":{"a":0,"k":0,"ix":4},"sa":{"a":0,"k":0,"ix":5},"nm":"Transform"}],"nm":"e","np":5,"cix":2,"bm":0,"ix":7,"mn":"ADBE Vector Group","hd":false}],"ip":0,"op":2700,"st":0,"bm":0}],"markers":[]}
